workcell/__init__.py
workcell/cli/__init__.py
workcell/cli/builder.py
workcell/cli/cli.py
workcell/cli/export.py
workcell/cli/utils.py
workcell/core/__init__.py
workcell/core/components.py
workcell/core/constants.py
workcell/core/errors.py
workcell/core/networking.py
workcell/core/routes.py
workcell/core/serialization.py
workcell/core/spec.py
workcell/core/utils.py
workcell/core/workcell.py
workcell/deploy/__init__.py
workcell/deploy/huggingface/__init__.py
workcell/deploy/huggingface/utils.py
workcell/deploy/huggingface/wrapper.py
workcell/integrations/types/__init__.py
workcell/integrations/types/altair.py
workcell/integrations/types/dummy.py
workcell/integrations/types/file.py
workcell/integrations/types/markdown.py
workcell/integrations/types/pandas.py
workcell/integrations/types/perspective.py
workcell/integrations/types/plotly.py
workcell/integrations/types/s3.py
workcell/integrations/types/svg.py
workcell/templates/frontend/index.html
workcell/templates/runtime/huggingface/python3.8/Dockerfile
workcell/templates/runtime/huggingface/python3.8/requirements.txt
workcell/templates/runtime/huggingface/python3.9/Dockerfile
workcell/templates/runtime/huggingface/python3.9/requirements.txt
workcell/templates/scaffold/huggingface/python3.8/Dockerfile
workcell/templates/scaffold/huggingface/python3.8/app.py
workcell/templates/scaffold/huggingface/python3.8/requirements.txt
workcell/templates/scaffold/huggingface/python3.8/workcell.yaml
workcell/templates/scaffold/huggingface/python3.9/Dockerfile
workcell/templates/scaffold/huggingface/python3.9/app.py
workcell/templates/scaffold/huggingface/python3.9/requirements.txt
workcell/templates/scaffold/huggingface/python3.9/workcell.yaml
workcell/utils/__init__.py
workcell/utils/encryptor.py
workcell/utils/processing_utils.py
workcell/utils/serve.py
workcell/utils/strings.py
workcell-0.0.38.dist-info/LICENSE
workcell-0.0.38.dist-info/METADATA
workcell-0.0.38.dist-info/WHEEL
workcell-0.0.38.dist-info/entry_points.txt
workcell-0.0.38.dist-info/RECORD
