Metadata-Version: 2.1
Name: workcell
Version: 0.0.38
Summary: Turn python function into microservice.
License: Apache-2.0
Author: jiandong
Author-email: jiandong@weanalyze.co
Requires-Python: >=3.8
Classifier: License :: OSI Approved :: Apache Software License
Classifier: Programming Language :: Python :: 3
Classifier: Programming Language :: Python :: 3.8
Classifier: Programming Language :: Python :: 3.9
Classifier: Programming Language :: Python :: 3.10
Classifier: Programming Language :: Python :: 3.11
Requires-Dist: altair (>=4.2.2,<5.0.0)
Requires-Dist: fastapi (>=0.85.1,<0.86.0)
Requires-Dist: huggingface-hub (>=0.12.0,<0.13.0)
Requires-Dist: jsonpickle (>=3.0.1,<4.0.0)
Requires-Dist: orjson (>=3.8.6,<4.0.0)
Requires-Dist: pandas (>=1.5.2,<2.0.0)
Requires-Dist: perspective-python (>=1.9.3,<2.0.0)
Requires-Dist: plotly (>=5.12.0,<6.0.0)
Requires-Dist: pyarrow (>=11.0.0,<12.0.0)
Requires-Dist: pydantic (>=1.10.2,<2.0.0)
Requires-Dist: python-dotenv (>=0.19.0,<0.20.0)
Requires-Dist: rich (>=13.3.3,<14.0.0)
Requires-Dist: typer (>=0.3.1,<0.4.0)
Requires-Dist: uvicorn (>=0.18.3,<0.19.0)
